mmoran0032/__init__.py
mmoran0032/cli.py
mmoran0032-2024.12.dist-info/METADATA
mmoran0032-2024.12.dist-info/WHEEL
mmoran0032-2024.12.dist-info/entry_points.txt
mmoran0032-2024.12.dist-info/top_level.txt
mmoran0032-2024.12.dist-info/RECORD
